setup.py
meg/__init__.py
meg/api.py
meg/app.py
meg/cfg.py
meg/config.default.yml
meg/constants.py
meg/db.py
meg/development.py
meg/email.py
meg/exception.py
meg/pgp.py
meg/production.py
meg/sks.py
meg/stalks.py
megserver.egg-info/PKG-INFO
megserver.egg-info/SOURCES.txt
megserver.egg-info/dependency_links.txt
megserver.egg-info/entry_points.txt
megserver.egg-info/requires.txt
megserver.egg-info/top_level.txt