Metadata-Version: 1.0
Name: megserver
Version: 0.6.0
Summary: Server component for MEG
Home-page: UNKNOWN
Author: Gregory Rehm
Author-email: UNKNOWN
License: UNKNOWN
Platform: UNKNOWN
